stelar_synth_corr_data/__init__.py
stelar_synth_corr_data/generate_synthetic_data.py
stelar_synth_corr_data/stelar.py
stelar_synth_corr_data-0.1.0.dist-info/METADATA
stelar_synth_corr_data-0.1.0.dist-info/WHEEL
stelar_synth_corr_data-0.1.0.dist-info/licenses/LICENSE
stelar_synth_corr_data-0.1.0.dist-info/RECORD
