Metadata-Version: 2.4
Name: stelar_synth_corr_data
Version: 0.1.0
Summary: STELAR Synthetic Correlation Data
Project-URL: Homepage, https://github.com/wiegerpunter/CorrSynth
Project-URL: Issues, https://github.com/wiegerpunter/CorrSynth/issues
Author-email: stelar_synth_corr_data <w.r.punter@tue.nl>
License-Expression: MIT
License-File: LICENSE
Classifier: Operating System :: OS Independent
Classifier: Programming Language :: Python :: 3
Requires-Python: >=3.8
